charnet/__init__.py
charnet/charnet.py
charnet/analysis/__init__.py
charnet/analysis/centrality_analysis.py
charnet/analysis/community_analysis.py
charnet/examples/__init__.py
charnet/examples/test.py
charnet/utils/__init__.py
charnet/utils/data_utils.py
charnet/utils/graph_utils.py
charnet/visualization/__init__.py
charnet/visualization/gravis_plotter.py
charnet/visualization/matplotlib_plotter.py
charnet/visualization/plotly_plotter.py
charnet/visualization/pyvis_plotter.py
charnet-0.0.4.dist-info/LICENSE
charnet-0.0.4.dist-info/METADATA
charnet-0.0.4.dist-info/WHEEL
charnet-0.0.4.dist-info/top_level.txt
charnet-0.0.4.dist-info/RECORD
