Metadata-Version: 2.1
Name: charnet
Version: 0.0.4
Summary: Character interaction temporal graph analysis
Home-page: https://github.com/MediaCompLab/CharNet
Author: Media Comprehension Lab
Author-email: shu13@gsu.edu
License: GPL-3.0
Classifier: Programming Language :: Python :: 3
Classifier: License :: OSI Approved :: GNU General Public License v3 (GPLv3)
Classifier: Operating System :: OS Independent
Requires-Python: >=3.6
License-File: LICENSE
Requires-Dist: pandas
Requires-Dist: networkx
Requires-Dist: numpy
Requires-Dist: matplotlib
Provides-Extra: all
Requires-Dist: plotly ; extra == 'all'
Requires-Dist: gravis ; extra == 'all'
Requires-Dist: pyvis ; extra == 'all'
Provides-Extra: dev
Requires-Dist: pytest (>=7.0) ; extra == 'dev'
Requires-Dist: twine (>=4.0.2) ; extra == 'dev'
